LICENSE
MANIFEST.in
README.rst
setup.py
demo/__init__.py
demo/manage.py
demo/core/__init__.py
demo/core/urls.py
demo/core/wsgi.py
demo/core/settings/__init__.py
demo/core/settings/demo.py
demo/main/__init__.py
demo/main/forms.py
demo/main/models.py
demo/main/tests.py
demo/main/views.py
django_multimail.egg-info/PKG-INFO
django_multimail.egg-info/SOURCES.txt
django_multimail.egg-info/dependency_links.txt
django_multimail.egg-info/not-zip-safe
django_multimail.egg-info/top_level.txt
multimail/__init__.py
multimail/admin.py
multimail/backends.py
multimail/models.py
multimail/settings.py
multimail/urls.py
multimail/util.py
multimail/views.py
multimail/templates/multimail/base_multimail_email.html
multimail/templates/multimail/base_multimail_email.txt
multimail/templates/multimail/verification_email.html
multimail/templates/multimail/verification_email.txt
tests/__init__.py
tests/test_email.py