Metadata-Version: 1.1
Name: django-multimail
Version: 0.1.4
Summary: Enable multiple email addresses per user in Django
Home-page: http://django-multimail.com
Author: scott2b <Scott B. Bradley>
Author-email: scott@scott2b.com
License: OSI Approved :: MIT License
Keywords: django,e-mail,email,multimail,multiple addresses
Platform: UNKNOWN
Classifier: Framework :: Django
Classifier: Development Status :: 4 - Beta
Classifier: Environment :: Web Environment
Classifier: Intended Audience :: Developers
Classifier: License :: OSI Approved :: MIT License
Classifier: Operating System :: OS Independent
Classifier: Programming Language :: Python
Classifier: Topic :: Software Development :: Libraries :: Python Modules
